{
    "products": [
        {
            "id": 1,
            "name": "Produto 1",
            "price": 299.50,
            "file": "//placehold.it/300x300",
            "description": "Some description..."
        },
        {
            "id": 2,
            "name": "Produto 2",
            "price": 299.50,
            "file": "//placehold.it/300x300",
            "description": "Some description..."
        },
        {
            "id": 3,
            "name": "Produto 3",
            "price": 299.50,
            "file": "//placehold.it/300x300",
            "description": "Some description..."
        },
        {
            "id": 4,
            "name": "Produto 4",
            "price": 299.50,
            "file": "//placehold.it/300x300",
            "description": "Some description..."
        }
    ]
}